[{"id":1,"first_name":"Franecki and Sons","address":"00240 Randy Pass","boylers":[54,30,44],"company":null},{"id":2,"first_name":"Gerlach, Jast and Bosco","address":"7481 Commercial Pass","boylers":[73,9,75],"company":11},{"id":3,"first_name":"Schmitt and Sons","address":"6 Autumn Leaf Lane","boylers":[97,84,91],"company":null},{"id":4,"first_name":"Ebert Group","address":"52879 Anzinger Junction","boylers":[98,25,5],"company":null},{"id":5,"first_name":"Bernier, Zboncak and Cremin","address":"9375 Parkside Park","boylers":[97,16,41],"company":null},{"id":6,"first_name":"Cormier, Heidenreich and Friesen","address":"0 Bowman Lane","boylers":[57,96,42],"company":82},{"id":7,"first_name":"Koch Inc","address":"6 Shasta Lane","boylers":[55,52,88],"company":null},{"id":8,"first_name":"Bernier LLC","address":"3026 Coleman Circle","boylers":[29,49,63],"company":55},{"id":9,"first_name":"Murazik, Stehr and Dare","address":"061 Magdeline Road","boylers":[94,20,57],"company":84},{"id":10,"first_name":"Murray LLC","address":"3499 Blackbird Center","boylers":[29,6,91],"company":20},{"id":11,"first_name":"Crist Group","address":"031 Hooker Road","boylers":[56,12,17],"company":27},{"id":12,"first_name":"Ratke Group","address":"2397 6th Park","boylers":[63,77,14],"company":94},{"id":13,"first_name":"Gibson, Crona and Feil","address":"14981 Emmet Plaza","boylers":[90,69,87],"company":null},{"id":16,"first_name":"Collins Group","address":"250 Elmside Pass","boylers":[62,88,38],"company":null},{"id":17,"first_name":"Lindgren, Rippin and Yost","address":"400 Texas Alley","boylers":[80,30,32],"company":null},{"id":18,"first_name":"Upton-Emard","address":"4139 International Center","boylers":[36,57,62],"company":null},{"id":19,"first_name":"Waelchi LLC","address":"290 Eggendart Street","boylers":[92,72,54],"company":null},{"id":20,"first_name":"Will, McDermott and Wolf","address":"188 Nevada Trail","boylers":[7,43,87],"company":10},{"id":21,"first_name":"Durgan, Lebsack and Hane","address":"4 Chive Way","boylers":[3,88,34],"company":null},{"id":22,"first_name":"Harvey and Sons","address":"56 Warner Point","boylers":[38,77,51],"company":null},{"id":23,"first_name":"Wiegand-Huels","address":"684 Bultman Lane","boylers":[37,6,48],"company":43},{"id":24,"first_name":"Schimmel-Bergnaum","address":"4 Lerdahl Terrace","boylers":[55,27,71],"company":null},{"id":25,"first_name":"Boyle-Zieme","address":"3 Dapin Circle","boylers":[41,23,77],"company":50},{"id":26,"first_name":"Collier, Murray and Windler","address":"4 Spaight Hill","boylers":[87,26,98],"company":null},{"id":27,"first_name":"Klocko, Harris and Bergnaum","address":"29 Farwell Junction","boylers":[37,77,39],"company":66},{"id":28,"first_name":"Sanford-Will","address":"5074 Arkansas Place","boylers":[84,51,89],"company":74},{"id":29,"first_name":"Reilly and Sons","address":"122 Homewood Circle","boylers":[90,38,16],"company":59},{"id":30,"first_name":"Bode-Heidenreich","address":"5815 Lawn Way","boylers":[29,47,91],"company":33},{"id":31,"first_name":"Ernser, Herman and Runolfsdottir","address":"1 Schlimgen Avenue","boylers":[79,18,85],"company":null},{"id":32,"first_name":"Rogahn, Kerluke and Konopelski","address":"82017 Ryan Way","boylers":[35,33,3],"company":null},{"id":33,"first_name":"Reinger LLC","address":"49937 Dexter Crossing","boylers":[43,80,78],"company":null},{"id":34,"first_name":"Altenwerth, Boehm and Huels","address":"21 Drewry Trail","boylers":[9,88,6],"company":null},{"id":35,"first_name":"Stoltenberg, Jerde and Waters","address":"9 Bartelt Pass","boylers":[37,21,4],"company":80},{"id":36,"first_name":"Pollich Group","address":"00035 Cherokee Place","boylers":[69,98,49],"company":34},{"id":37,"first_name":"Mraz Group","address":"2815 Northfield Terrace","boylers":[82,39,65],"company":65},{"id":38,"first_name":"Corkery-Lubowitz","address":"3 Westport Pass","boylers":[4,34,56],"company":null},{"id":39,"first_name":"Gorczany-Mante","address":"3 Merrick Hill","boylers":[66,34,76],"company":22},{"id":40,"first_name":"Sporer-Walsh","address":"46543 Maple Wood Trail","boylers":[56,34,2],"company":null},{"id":41,"first_name":"Tillman LLC","address":"593 Browning Terrace","boylers":[65,77,64],"company":3},{"id":42,"first_name":"Nader Inc","address":"76120 Bultman Trail","boylers":[35,65,94],"company":22},{"id":43,"first_name":"Pfeffer, Rodriguez and Spencer","address":"28979 Larry Crossing","boylers":[8,3,97],"company":null},{"id":44,"first_name":"Emard Group","address":"6091 Dayton Trail","boylers":[20,58,1],"company":62},{"id":45,"first_name":"Schmidt-Dietrich","address":"1449 Namekagon Road","boylers":[55,47,79],"company":null},{"id":46,"first_name":"Goldner, McCullough and Boyle","address":"05909 Kinsman Junction","boylers":[32,35,69],"company":48},{"id":47,"first_name":"Parisian Group","address":"73420 Westport Pass","boylers":[23,73,82],"company":73},{"id":48,"first_name":"Treutel Group","address":"0688 Westport Avenue","boylers":[38,9,61],"company":66},{"id":49,"first_name":"Stiedemann and Sons","address":"4 Schurz Crossing","boylers":[78,22,36],"company":39},{"id":50,"first_name":"Lubowitz and Sons","address":"9270 Northwestern Trail","boylers":[28,74,54],"company":18},{"id":51,"first_name":"Koelpin-Koss","address":"3642 David Lane","boylers":[9,89,77],"company":26},{"id":52,"first_name":"Green-Schimmel","address":"8 Fremont Point","boylers":[67,27,46],"company":7},{"id":53,"first_name":"Pouros-Murazik","address":"0052 Reinke Park","boylers":[2,78,83],"company":null},{"id":54,"first_name":"Hudson LLC","address":"27669 Nevada Court","boylers":[56,65,47],"company":null},{"id":55,"first_name":"Hessel-Krajcik","address":"0 Lerdahl Road","boylers":[64,50,27],"company":null},{"id":56,"first_name":"Heaney and Sons","address":"501 Ruskin Pass","boylers":[16,35,53],"company":null},{"id":57,"first_name":"Tillman-Bechtelar","address":"5898 Elmside Point","boylers":[15,71,79],"company":null},{"id":58,"first_name":"Kris, Padberg and Schuppe","address":"311 Lyons Alley","boylers":[67,16,20],"company":75},{"id":59,"first_name":"Jakubowski-Osinski","address":"5 Prentice Street","boylers":[44,45,45],"company":null},{"id":60,"first_name":"Hirthe Inc","address":"35676 Thackeray Court","boylers":[71,61,50],"company":92},{"id":61,"first_name":"Considine-O'Keefe","address":"08 Express Avenue","boylers":[17,40,57],"company":2},{"id":62,"first_name":"Wiegand, Padberg and Dach","address":"20465 Kinsman Terrace","boylers":[94,45,82],"company":null},{"id":63,"first_name":"Leffler-Reilly","address":"9 Elgar Drive","boylers":[99,44,6],"company":40},{"id":64,"first_name":"Bosco, Cummerata and Lang","address":"9236 Weeping Birch Street","boylers":[75,49,87],"company":null},{"id":65,"first_name":"Conn, Jerde and Altenwerth","address":"5 Heffernan Pass","boylers":[35,44,65],"company":46},{"id":66,"first_name":"Hyatt and Sons","address":"9552 Valley Edge Parkway","boylers":[62,10,62],"company":22},{"id":67,"first_name":"Huel-Lockman","address":"87 Bunker Hill Lane","boylers":[13,25,79],"company":87},{"id":68,"first_name":"Lueilwitz, Marks and Wilkinson","address":"4903 Farragut Park","boylers":[70,43,91],"company":null},{"id":69,"first_name":"Weissnat-Herman","address":"124 Montana Avenue","boylers":[16,89,89],"company":60},{"id":70,"first_name":"Brown, Larson and Ruecker","address":"46 Homewood Avenue","boylers":[74,56,66],"company":null},{"id":71,"first_name":"Braun, Kautzer and Swaniawski","address":"657 Sycamore Way","boylers":[72,49,97],"company":null},{"id":72,"first_name":"Turcotte, Metz and West","address":"49261 Bunting Court","boylers":[93,66,52],"company":40},{"id":73,"first_name":"Koch, Skiles and Stoltenberg","address":"056 Goodland Circle","boylers":[81,20,7],"company":null},{"id":74,"first_name":"Leffler-Torp","address":"6 Gerald Plaza","boylers":[40,33,3],"company":19},{"id":75,"first_name":"Muller and Sons","address":"7100 Hintze Parkway","boylers":[69,73,48],"company":null},{"id":76,"first_name":"Hudson, Parker and Cole","address":"45986 Paget Crossing","boylers":[15,54,32],"company":89},{"id":77,"first_name":"Volkman and Sons","address":"644 Crowley Avenue","boylers":[92,34,75],"company":null},{"id":78,"first_name":"Rogahn LLC","address":"91341 Jenifer Point","boylers":[56,2,57],"company":62},{"id":79,"first_name":"Fadel-Maggio","address":"433 Dahle Hill","boylers":[8,92,21],"company":74},{"id":80,"first_name":"Sporer-Effertz","address":"1480 Hagan Drive","boylers":[70,31,78],"company":29},{"id":81,"first_name":"Yundt and Sons","address":"2 Maple Wood Place","boylers":[37,42,25],"company":37},{"id":82,"first_name":"Walker-Koss","address":"29 South Drive","boylers":[27,36,95],"company":58},{"id":83,"first_name":"Berge Inc","address":"3 Vahlen Road","boylers":[16,87,29],"company":85},{"id":84,"first_name":"Dare-Sipes","address":"6738 Huxley Crossing","boylers":[82,34,99],"company":null},{"id":85,"first_name":"Abbott-Graham","address":"0 Grayhawk Circle","boylers":[60,90,27],"company":null},{"id":86,"first_name":"Boyle-Hammes","address":"7938 Forest Dale Lane","boylers":[4,29,86],"company":null},{"id":87,"first_name":"McLaughlin-Mante","address":"940 Caliangt Circle","boylers":[4,51,17],"company":100},{"id":88,"first_name":"McDermott-Ullrich","address":"03546 Rutledge Lane","boylers":[82,60,81],"company":82},{"id":89,"first_name":"Walter-Stamm","address":"566 Dorton Pass","boylers":[92,94,84],"company":41},{"id":90,"first_name":"VonRueden, Grimes and Towne","address":"00 Vidon Avenue","boylers":[44,59,95],"company":null},{"id":91,"first_name":"Kuphal, White and Conn","address":"39 Katie Trail","boylers":[53,47,55],"company":47},{"id":92,"first_name":"Yost-Haag","address":"8599 Sommers Court","boylers":[13,67,27],"company":null},{"id":93,"first_name":"Parker Inc","address":"7 Hollow Ridge Junction","boylers":[71,34,21],"company":null},{"id":94,"first_name":"Block, Fisher and Rosenbaum","address":"117 Bunting Circle","boylers":[30,44,76],"company":null},{"id":95,"first_name":"Halvorson-Ratke","address":"519 Waubesa Parkway","boylers":[22,95,91],"company":null},{"id":96,"first_name":"Medhurst-Bruen","address":"193 Northland Court","boylers":[29,39,23],"company":null},{"id":97,"first_name":"Swift Inc","address":"722 Hooker Trail","boylers":[1,44,37],"company":null},{"id":98,"first_name":"Orn Inc","address":"86848 Dawn Park","boylers":[13,68,40],"company":null},{"id":99,"first_name":"Carroll-Gerlach","address":"6 Del Sol Pass","boylers":[44,18,54],"company":44},{"id":100,"first_name":"Cole Inc","address":"32 Dryden Center","boylers":[32,87,76],"company":null}]